geogeometry/__init__.py
geogeometry/geo_io/CadReader.py
geogeometry/geo_io/__init__.py
geogeometry/geo_io/readers/CsvReader.py
geogeometry/geo_io/readers/DxfReader.py
geogeometry/geo_io/readers/RhinoReader.py
geogeometry/geo_io/readers/StlReader.py
geogeometry/geo_io/readers/__init__.py
geogeometry/geo_io/readers/dxf_components/DxfEntityHandler.py
geogeometry/geo_io/readers/dxf_components/EntityHandlerRegistry.py
geogeometry/geo_io/readers/dxf_components/__init__.py
geogeometry/geometry/__init__.py
geogeometry/geometry/block/Block.py
geogeometry/geometry/block/__init__.py
geogeometry/geometry/block/components/BlockMetrics.py
geogeometry/geometry/block/components/BlockPlotter.py
geogeometry/geometry/block/components/BlockProperties.py
geogeometry/geometry/block/components/BlockRepresentation.py
geogeometry/geometry/block/components/__init__.py
geogeometry/geometry/circle/Circle.py
geogeometry/geometry/circle/__init__.py
geogeometry/geometry/circle/components/CircleMetrics.py
geogeometry/geometry/circle/components/CirclePlotter.py
geogeometry/geometry/circle/components/CircleProperties.py
geogeometry/geometry/circle/components/__init__.py
geogeometry/geometry/cylinder/Cylinder.py
geogeometry/geometry/cylinder/__init__.py
geogeometry/geometry/cylinder/components/CylinderProperties.py
geogeometry/geometry/cylinder/components/__init__.py
geogeometry/geometry/model/GeometryModel.py
geogeometry/geometry/model/GeometryModelsCollection.py
geogeometry/geometry/model/__init__.py
geogeometry/geometry/model/collection_components/GeometryModelsCollectionPlotter.py
geogeometry/geometry/model/collection_components/__init__.py
geogeometry/geometry/model/components/GeometryModelMetrics.py
geogeometry/geometry/model/components/GeometryModelPlotter.py
geogeometry/geometry/model/components/GeometryModelProperties.py
geogeometry/geometry/model/components/__init__.py
geogeometry/geometry/operations/Angles.py
geogeometry/geometry/operations/Collinearity.py
geogeometry-0.0.5.dist-info/LICENSE
geogeometry-0.0.5.dist-info/METADATA
geogeometry-0.0.5.dist-info/WHEEL
geogeometry-0.0.5.dist-info/top_level.txt
geogeometry-0.0.5.dist-info/RECORD
