Metadata-Version: 2.1
Name: geogeometry
Version: 0.0.5
Summary: A Python geometrical library made for geotechnical engineering.
Author: Jorge Martinez
Author-email: jmartinez@gmintec.com
License: MIT
Classifier: Programming Language :: Python :: 3
Classifier: License :: OSI Approved :: MIT License
Classifier: Operating System :: OS Independent
Requires-Python: >=3.10
License-File: LICENSE
Requires-Dist: pre-commit ~=4.0.1
Requires-Dist: twine ~=6.0.1
Requires-Dist: numpy ~=2.1.3
Requires-Dist: shapely ~=2.0.6
Requires-Dist: trimesh ~=4.5.3
Requires-Dist: matplotlib ~=3.9.3
Requires-Dist: ezdxf ~=1.3.4
Requires-Dist: rhino3dm ~=8.9.0
Requires-Dist: pyvista ~=0.44.2
